README.rst
setup.py
automover/__init__.py
automover/client.py
automover/cmd.py
automover/remover.py
automover/section.py
automover/utils.py
automover/clients/__init__.py
automover/clients/rtorrent.py
automover/sections/__init__.py
automover/sections/movies.py
automover/sections/stuff.py
automover/sections/tv.py
rtorrent_automover.egg-info/PKG-INFO
rtorrent_automover.egg-info/SOURCES.txt
rtorrent_automover.egg-info/dependency_links.txt
rtorrent_automover.egg-info/entry_points.txt
rtorrent_automover.egg-info/requires.txt
rtorrent_automover.egg-info/top_level.txt