Metadata-Version: 1.0
Name: rtorrent-automover
Version: 2.3.1
Summary: Automoving torrents.
Home-page: https://github.com/johndoee/
Author: Anders Jensen
Author-email: johndoee+autotorrent@tidalstream.org
License: BSD-new
Platform: UNKNOWN
